docs/Makefile
docs/conf.py
docs/index.rst
docs/make.bat
docs/refs.bib
docs/_static/example.ecsv
docs/_static/example.gif
docs/_static/css/risk_table.css
docs/design/index.rst
docs/design/milp.rst
docs/dev/changes.rst
docs/dev/contributing.rst
docs/dev/index.rst
docs/dev/npr7150.rst
docs/dev/related.rst
docs/dev/testing.rst
docs/guide/cli.rst
docs/guide/constraints.rst
docs/guide/dynamics.rst
docs/guide/fov.rst
docs/guide/index.rst
docs/guide/milp.rst
docs/guide/missions.rst
docs/guide/observer.rst
docs/guide/skygrid.rst
docs/guide/synphot.rst
docs/guide/utils.rst
docs/install/cplex.rst
docs/install/deploy.rst
docs/install/gurobi.rst
docs/install/index.rst
docs/scenarios/dorado.rst
docs/scenarios/index.rst
docs/scenarios/sedmachine.rst
docs/scenarios/ztf.rst
licenses/DORADO_LICENSE.txt
licenses/LICENSE.rst
licenses/README.rst
licenses/TEMPLATE_LICENCE.rst
m4opt/__init__.py
m4opt/_version.py
m4opt/conftest.py
m4opt/milp.py
m4opt/py.typed
m4opt/_cli/__init__.py
m4opt/_cli/animate.py
m4opt/_cli/core.py
m4opt/_cli/prime.py
m4opt/_cli/schedule.py
m4opt/_cli/tests/__init__.py
m4opt/_cli/tests/conftest.py
m4opt/_cli/tests/test_core.py
m4opt/_cli/tests/test_end_to_end.py
m4opt/_cli/tests/data/800.fits
m4opt/constraints/__init__.py
m4opt/constraints/_airmass.py
m4opt/constraints/_atnight.py
m4opt/constraints/_body_separation.py
m4opt/constraints/_core.py
m4opt/constraints/_earth_limb.py
m4opt/constraints/_galactic.py
m4opt/constraints/_logical.py
m4opt/constraints/_positional.py
m4opt/constraints/_radiation.py
m4opt/constraints/tests/__init__.py
m4opt/constraints/tests/test_body_separation.py
m4opt/constraints/tests/test_earth_limb.py
m4opt/constraints/tests/test_galactic.py
m4opt/constraints/tests/test_positional.py
m4opt/dynamics/__init__.py
m4opt/dynamics/_roll.py
m4opt/dynamics/_slew.py
m4opt/dynamics/tests/__init__.py
m4opt/dynamics/tests/test_roll.py
m4opt/extern/__init__.py
m4opt/fov/__init__.py
m4opt/fov/_core.py
m4opt/missions/__init__.py
m4opt/missions/_core.py
m4opt-2.3.1.dist-info/METADATA
m4opt-2.3.1.dist-info/WHEEL
m4opt-2.3.1.dist-info/entry_points.txt
m4opt-2.3.1.dist-info/top_level.txt
m4opt-2.3.1.dist-info/RECORD
