Metadata-Version: 2.4
Name: m4opt
Version: 2.3.1
Summary: Multi-Mission Multi-Messenger Observation Planning Toolkit
Author-email: M4OPT Developers <leo.singer@ligo.org>
License-Expression: BSD-3-Clause
Project-URL: Homepage, https://m4opt.readthedocs.io/
Project-URL: Bug Tracker, https://github.com/m4opt/m4opt/issues
Project-URL: Change Log, https://m4opt.readthedocs.io/en/latest/changes.html
Project-URL: Documentation, https://m4opt.readthedocs.io/
Project-URL: GitHub, https://github.com/m4opt/m4opt
Classifier: Development Status :: 3 - Alpha
Classifier: Environment :: Console
Classifier: Intended Audience :: Science/Research
Classifier: Operating System :: MacOS
Classifier: Operating System :: POSIX :: Linux
Classifier: Programming Language :: Python :: 3.11
Classifier: Programming Language :: Python :: 3.12
Classifier: Topic :: Scientific/Engineering :: Astronomy
Classifier: Typing :: Typed
Requires-Python: >=3.11
Requires-Dist: aep8
Requires-Dist: antiprism-python
Requires-Dist: astropy>=7.1.0
Requires-Dist: astropy-healpix
Requires-Dist: astroquery
Requires-Dist: click>=8.2.0
Requires-Dist: cplex
Requires-Dist: docplex
Requires-Dist: dust-extinction
Requires-Dist: dustmaps
Requires-Dist: ligo.skymap>=2.4.0
Requires-Dist: networkx
Requires-Dist: numpy>=2.1.0
Requires-Dist: regions
Requires-Dist: pymetis
Requires-Dist: satellitetle
Requires-Dist: scipy
Requires-Dist: sgp4
Requires-Dist: spiceypy
Requires-Dist: sympy
Requires-Dist: synphot
Requires-Dist: typer>=0.16.0
Requires-Dist: typing_extensions; python_version < "3.12"
Requires-Dist: xdg-base-dirs
Provides-Extra: test
Requires-Dist: astroplan; extra == "test"
Requires-Dist: networkx; extra == "test"
Requires-Dist: sphinxcontrib-bibtex; extra == "test"
Requires-Dist: pytest-astropy; extra == "test"
Provides-Extra: docs
Requires-Dist: pysiaf; extra == "docs"
Requires-Dist: sphinx-astropy[confv2]; extra == "docs"
Requires-Dist: sphinxcontrib-bibtex; extra == "docs"
Requires-Dist: sphinxcontrib-typer; extra == "docs"
